Rryyz/__init__.py
Rryyz/core.py
Rryyz/core_simple.py
Rryyz/cuda.py
Rryyz/dataloaders.py
Rryyz/datasets.py
Rryyz/functions.py
Rryyz/layers.py
Rryyz/models.py
Rryyz/optimizers.py
Rryyz/transforms.py
Rryyz/utils.py
Rryyz-0.0.3.dist-info/LICENSE
Rryyz-0.0.3.dist-info/METADATA
Rryyz-0.0.3.dist-info/WHEEL
Rryyz-0.0.3.dist-info/top_level.txt
Rryyz-0.0.3.dist-info/RECORD
