Metadata-Version: 2.1
Name: Rryyz
Version: 0.0.3
Summary: 一个轻巧便捷的深度学习框架
Author-email: 魔法少女小蓉 <1296811180@qq.com>
Classifier: Programming Language :: Python :: 3
Classifier: License :: OSI Approved :: MIT License
Classifier: Operating System :: OS Independent
Requires-Python: >=3.3
License-File: LICENSE
